{"Aspinwall Dist 1": {"Election Day": 156, "Absentee": 22, "Provisional": 0, "Total": 178}, "Aspinwall Dist 2": {"Election Day": 102, "Absentee": 18, "Provisional": 0, "Total": 120}, "Aspinwall Dist 3": {"Election Day": 122, "Absentee": 34, "Provisional": 0, "Total": 156}, "Blawnox": {"Election Day": 85, "Absentee": 23, "Provisional": 0, "Total": 108}, "Fox Chapel Dist 1": {"Election Day": 94, "Absentee": 37, "Provisional": 0, "Total": 131}, "Fox Chapel Dist 2": {"Election Day": 125, "Absentee": 27, "Provisional": 0, "Total": 152}, "Fox Chapel Dist 3": {"Election Day": 97, "Absentee": 18, "Provisional": 0, "Total": 115}, "Fox Chapel Dist 4": {"Election Day": 130, "Absentee": 44, "Provisional": 0, "Total": 174}, "Fox Chapel Dist 5": {"Election Day": 101, "Absentee": 20, "Provisional": 0, "Total": 121}, "Indiana Dist 1": {"Election Day": 52, "Absentee": 16, "Provisional": 0, "Total": 68}, "Indiana Dist 2": {"Election Day": 59, "Absentee": 14, "Provisional": 0, "Total": 73}, "Indiana Dist 3": {"Election Day": 44, "Absentee": 23, "Provisional": 0, "Total": 67}, "Indiana Dist 4": {"Election Day": 87, "Absentee": 30, "Provisional": 0, "Total": 117}, "Indiana Dist 5": {"Election Day": 68, "Absentee": 23, "Provisional": 0, "Total": 91}, "O'Hara Ward 1 Dist 1": {"Election Day": 74, "Absentee": 36, "Provisional": 0, "Total": 110}, "O'Hara Ward 1 Dist 2": {"Election Day": 63, "Absentee": 31, "Provisional": 0, "Total": 94}, "O'Hara Ward 2 Dist 1": {"Election Day": 41, "Absentee": 16, "Provisional": 0, "Total": 57}, "O'Hara Ward 2 Dist 2": {"Election Day": 53, "Absentee": 23, "Provisional": 0, "Total": 76}, "O'Hara Ward 3 Dist 1": {"Election Day": 39, "Absentee": 10, "Provisional": 0, "Total": 49}, "O'Hara Ward 3 Dist 2": {"Election Day": 35, "Absentee": 11, "Provisional": 0, "Total": 46}, "O'Hara Ward 4 Dist 1": {"Election Day": 57, "Absentee": 40, "Provisional": 0, "Total": 97}, "O'Hara Ward 4 Dist 2": {"Election Day": 73, "Absentee": 34, "Provisional": 0, "Total": 107}, "O'Hara Ward 5 Dist 1": {"Election Day": 0, "Absentee": 22, "Provisional": 0, "Total": 22}, "O'Hara Ward 5 Dist 2": {"Election Day": 77, "Absentee": 35, "Provisional": 0, "Total": 112}, "Sharpsburg Dist 1": {"Election Day": 34, "Absentee": 9, "Provisional": 0, "Total": 43}, "Sharpsburg Dist 2": {"Election Day": 38, "Absentee": 9, "Provisional": 0, "Total": 47}, "Sharpsburg Dist 3": {"Election Day": 61, "Absentee": 3, "Provisional": 0, "Total": 64}}