{"DUQUESNE WARD 1 DIST 1": {"Election Day": 38, "Absentee": 15, "Provisional": 0, "Total": 53}, "DUQUESNE WARD 1 DIST 2": {"Election Day": 32, "Absentee": 12, "Provisional": 0, "Total": 44}, "DUQUESNE WARD 1 DIST 3": {"Election Day": 25, "Absentee": 8, "Provisional": 0, "Total": 33}, "DUQUESNE WARD 1 DIST 4": {"Election Day": 10, "Absentee": 6, "Provisional": 0, "Total": 16}, "DUQUESNE WARD 2 DIST 1": {"Election Day": 43, "Absentee": 18, "Provisional": 0, "Total": 61}, "DUQUESNE WARD 2 DIST 2": {"Election Day": 41, "Absentee": 14, "Provisional": 0, "Total": 55}, "DUQUESNE WARD 2 DIST 3": {"Election Day": 46, "Absentee": 11, "Provisional": 2, "Total": 59}, "DUQUESNE WARD 3 DIST 1": {"Election Day": 24, "Absentee": 9, "Provisional": 0, "Total": 33}, "DUQUESNE WARD 3 DIST 2": {"Election Day": 7, "Absentee": 6, "Provisional": 0, "Total": 13}, "DUQUESNE WARD 3 DIST 3": {"Election Day": 57, "Absentee": 36, "Provisional": 2, "Total": 95}}