{"MILLVALE DIST 2": {"Election Day": 10, "Absentee": 1, "Provisional": 0, "Total": 11}, "MILLVALE DIST 4": {"Election Day": 17, "Absentee": 1, "Provisional": 0, "Total": 18}, "MILLVALE DIST 5": {"Election Day": 8, "Absentee": 0, "Provisional": 0, "Total": 8}, "RESERVE WARD 1": {"Election Day": 11, "Absentee": 2, "Provisional": 1, "Total": 14}, "RESERVE WARD 2": {"Election Day": 24, "Absentee": 3, "Provisional": 0, "Total": 27}, "RESERVE WARD 3": {"Election Day": 16, "Absentee": 6, "Provisional": 0, "Total": 22}, "RESERVE WARD 4": {"Election Day": 18, "Absentee": 4, "Provisional": 0, "Total": 22}, "SHALER WARD 1 DIST 1": {"Election Day": 22, "Absentee": 2, "Provisional": 0, "Total": 24}, "SHALER WARD 1 DIST 3": {"Election Day": 17, "Absentee": 2, "Provisional": 0, "Total": 19}, "SHALER WARD 1 DIST 4": {"Election Day": 22, "Absentee": 3, "Provisional": 0, "Total": 25}, "SHALER WARD 2 DIST 1": {"Election Day": 51, "Absentee": 11, "Provisional": 0, "Total": 62}, "SHALER WARD 2 DIST 2": {"Election Day": 32, "Absentee": 8, "Provisional": 3, "Total": 43}, "SHALER WARD 2 DIST 3": {"Election Day": 26, "Absentee": 6, "Provisional": 0, "Total": 32}, "SHALER WARD 2 DIST 4": {"Election Day": 36, "Absentee": 3, "Provisional": 0, "Total": 39}, "SHALER WARD 5 DIST 4": {"Election Day": 21, "Absentee": 4, "Provisional": 0, "Total": 25}}