{"Robinson Dist 1": {"Election Day": 0, "Absentee": 68, "Provisional": 0, "Total": 68}, "Robinson Dist 2": {"Election Day": 0, "Absentee": 26, "Provisional": 0, "Total": 26}, "Robinson Dist 3": {"Election Day": 0, "Absentee": 13, "Provisional": 0, "Total": 13}, "Robinson Dist 4": {"Election Day": 0, "Absentee": 25, "Provisional": 0, "Total": 25}, "Robinson Dist 5": {"Election Day": 0, "Absentee": 19, "Provisional": 0, "Total": 19}, "Robinson Dist 6": {"Election Day": 0, "Absentee": 18, "Provisional": 0, "Total": 18}, "Robinson Dist 7": {"Election Day": 0, "Absentee": 40, "Provisional": 0, "Total": 40}, "Robinson Dist 8": {"Election Day": 0, "Absentee": 27, "Provisional": 0, "Total": 27}, "Robinson Dist 9": {"Election Day": 0, "Absentee": 86, "Provisional": 0, "Total": 86}}