{"Jefferson Hl Dist 1": {"Election Day": 0, "Absentee": 136, "Provisional": 0, "Total": 136}, "Jefferson Hl Dist 2": {"Election Day": 0, "Absentee": 29, "Provisional": 0, "Total": 29}, "Jefferson Hl Dist 3": {"Election Day": 0, "Absentee": 54, "Provisional": 0, "Total": 54}, "Jefferson Hl Dist 4": {"Election Day": 33, "Absentee": 44, "Provisional": 0, "Total": 77}, "Jefferson Hl Dist 5": {"Election Day": 0, "Absentee": 139, "Provisional": 0, "Total": 139}, "Jefferson Hl Dist 6": {"Election Day": 0, "Absentee": 29, "Provisional": 0, "Total": 29}, "Jefferson Hl Dist 7": {"Election Day": 0, "Absentee": 28, "Provisional": 0, "Total": 28}, "Jefferson Hl Dist 8": {"Election Day": 95, "Absentee": 94, "Provisional": 0, "Total": 189}}