{"Oakmont Dist 1": {"Election Day": 9, "Absentee": 4, "Provisional": 0, "Total": 13}, "Oakmont Dist 2": {"Election Day": 0, "Absentee": 9, "Provisional": 0, "Total": 9}, "Oakmont Dist 3": {"Election Day": 11, "Absentee": 7, "Provisional": 0, "Total": 18}, "Oakmont Dist 4": {"Election Day": 18, "Absentee": 2, "Provisional": 0, "Total": 20}, "Oakmont Dist 5": {"Election Day": 6, "Absentee": 2, "Provisional": 0, "Total": 8}, "Oakmont Dist 6": {"Election Day": 12, "Absentee": 3, "Provisional": 0, "Total": 15}}