{"BETHEL PARK WARD 1 DIST 1": {"Election Day": 34, "Absentee": 32, "Provisional": 0, "Total": 66}, "BETHEL PARK WARD 1 DIST 2": {"Election Day": 49, "Absentee": 23, "Provisional": 0, "Total": 72}, "BETHEL PARK WARD 1 DIST 3": {"Election Day": 51, "Absentee": 37, "Provisional": 0, "Total": 88}, "BETHEL PARK WARD 2 DIST 1": {"Election Day": 40, "Absentee": 29, "Provisional": 0, "Total": 69}, "BETHEL PARK WARD 2 DIST 2": {"Election Day": 46, "Absentee": 31, "Provisional": 0, "Total": 77}, "BETHEL PARK WARD 2 DIST 3": {"Election Day": 36, "Absentee": 48, "Provisional": 0, "Total": 84}, "BETHEL PARK WARD 3 DIST 1": {"Election Day": 43, "Absentee": 19, "Provisional": 0, "Total": 62}, "BETHEL PARK WARD 3 DIST 2": {"Election Day": 39, "Absentee": 57, "Provisional": 0, "Total": 96}, "BETHEL PARK WARD 3 DIST 3": {"Election Day": 41, "Absentee": 43, "Provisional": 0, "Total": 84}, "BETHEL PARK WARD 4 DIST 1": {"Election Day": 43, "Absentee": 66, "Provisional": 1, "Total": 110}, "BETHEL PARK WARD 4 DIST 2": {"Election Day": 29, "Absentee": 30, "Provisional": 1, "Total": 60}, "BETHEL PARK WARD 4 DIST 3": {"Election Day": 32, "Absentee": 31, "Provisional": 0, "Total": 63}, "BETHEL PARK WARD 5 DIST 1": {"Election Day": 28, "Absentee": 21, "Provisional": 0, "Total": 49}, "BETHEL PARK WARD 5 DIST 2": {"Election Day": 29, "Absentee": 23, "Provisional": 0, "Total": 52}, "BETHEL PARK WARD 5 DIST 3": {"Election Day": 46, "Absentee": 83, "Provisional": 0, "Total": 129}, "BETHEL PARK WARD 6 DIST 1": {"Election Day": 70, "Absentee": 53, "Provisional": 0, "Total": 123}, "BETHEL PARK WARD 6 DIST 2": {"Election Day": 48, "Absentee": 40, "Provisional": 0, "Total": 88}, "BETHEL PARK WARD 6 DIST 3": {"Election Day": 39, "Absentee": 31, "Provisional": 1, "Total": 71}, "BETHEL PARK WARD 7 DIST 1": {"Election Day": 39, "Absentee": 42, "Provisional": 1, "Total": 82}, "BETHEL PARK WARD 7 DIST 2": {"Election Day": 47, "Absentee": 43, "Provisional": 2, "Total": 92}, "BETHEL PARK WARD 7 DIST 3": {"Election Day": 25, "Absentee": 19, "Provisional": 1, "Total": 45}, "BETHEL PARK WARD 8 DIST 1": {"Election Day": 30, "Absentee": 22, "Provisional": 1, "Total": 53}, "BETHEL PARK WARD 8 DIST 2": {"Election Day": 8, "Absentee": 16, "Provisional": 0, "Total": 24}, "BETHEL PARK WARD 8 DIST 3": {"Election Day": 77, "Absentee": 68, "Provisional": 0, "Total": 145}, "BETHEL PARK WARD 8 DIST 4": {"Election Day": 22, "Absentee": 21, "Provisional": 0, "Total": 43}, "BETHEL PARK WARD 9 DIST 1": {"Election Day": 27, "Absentee": 17, "Provisional": 0, "Total": 44}, "BETHEL PARK WARD 9 DIST 2": {"Election Day": 25, "Absentee": 19, "Provisional": 0, "Total": 44}, "BETHEL PARK WARD 9 DIST 3": {"Election Day": 55, "Absentee": 55, "Provisional": 0, "Total": 110}, "CASL SHANNON DIST 6": {"Election Day": 8, "Absentee": 9, "Provisional": 0, "Total": 17}}