{"Monroeville Ward 1 Dist 1": {"Election Day": 0, "Absentee": 51, "Provisional": 0, "Total": 51}, "Monroeville Ward 1 Dist 2": {"Election Day": 0, "Absentee": 77, "Provisional": 0, "Total": 77}, "Monroeville Ward 1 Dist 3": {"Election Day": 0, "Absentee": 94, "Provisional": 0, "Total": 94}, "Monroeville Ward 1 Dist 4": {"Election Day": 66, "Absentee": 67, "Provisional": 0, "Total": 133}, "Monroeville Ward 2 Dist 1": {"Election Day": 0, "Absentee": 91, "Provisional": 0, "Total": 91}, "Monroeville Ward 2 Dist 2": {"Election Day": 0, "Absentee": 120, "Provisional": 0, "Total": 120}, "Monroeville Ward 2 Dist 3": {"Election Day": 0, "Absentee": 170, "Provisional": 0, "Total": 170}, "Monroeville Ward 3 Dist 1": {"Election Day": 0, "Absentee": 146, "Provisional": 0, "Total": 146}, "Monroeville Ward 3 Dist 2": {"Election Day": 130, "Absentee": 61, "Provisional": 0, "Total": 191}, "Monroeville Ward 3 Dist 3": {"Election Day": 185, "Absentee": 100, "Provisional": 0, "Total": 285}, "Monroeville Ward 3 Dist 4": {"Election Day": 80, "Absentee": 46, "Provisional": 0, "Total": 126}, "Monroeville Ward 4 Dist 1": {"Election Day": 104, "Absentee": 65, "Provisional": 0, "Total": 169}, "Monroeville Ward 4 Dist 2": {"Election Day": 173, "Absentee": 82, "Provisional": 0, "Total": 255}, "Monroeville Ward 4 Dist 3": {"Election Day": 177, "Absentee": 101, "Provisional": 0, "Total": 278}, "Monroeville Ward 5 Dist 1": {"Election Day": 98, "Absentee": 64, "Provisional": 0, "Total": 162}, "Monroeville Ward 5 Dist 2": {"Election Day": 64, "Absentee": 84, "Provisional": 0, "Total": 148}, "Monroeville Ward 5 Dist 3": {"Election Day": 112, "Absentee": 103, "Provisional": 0, "Total": 215}, "Monroeville Ward 5 Dist 4": {"Election Day": 42, "Absentee": 48, "Provisional": 0, "Total": 90}, "Monroeville Ward 6 Dist 1": {"Election Day": 128, "Absentee": 86, "Provisional": 0, "Total": 214}, "Monroeville Ward 6 Dist 2": {"Election Day": 0, "Absentee": 84, "Provisional": 0, "Total": 84}, "Monroeville Ward 6 Dist 3": {"Election Day": 97, "Absentee": 49, "Provisional": 0, "Total": 146}, "Monroeville Ward 6 Dist 4": {"Election Day": 24, "Absentee": 44, "Provisional": 0, "Total": 68}, "Monroeville Ward 7 Dist 1": {"Election Day": 221, "Absentee": 164, "Provisional": 0, "Total": 385}, "Monroeville Ward 7 Dist 2": {"Election Day": 0, "Absentee": 85, "Provisional": 0, "Total": 85}, "Monroeville Ward 7 Dist 3": {"Election Day": 98, "Absentee": 64, "Provisional": 0, "Total": 162}}