{"Glassport Dist 1": {"Election Day": 0, "Absentee": 1, "Provisional": 0, "Total": 1}, "Glassport Dist 2": {"Election Day": 0, "Absentee": 0, "Provisional": 0, "Total": 0}, "Glassport Dist 3": {"Election Day": 0, "Absentee": 0, "Provisional": 0, "Total": 0}, "Glassport Dist 4": {"Election Day": 0, "Absentee": 0, "Provisional": 0, "Total": 0}, "Glassport Dist 5": {"Election Day": 0, "Absentee": 3, "Provisional": 0, "Total": 3}, "Glassport Dist 6": {"Election Day": 0, "Absentee": 0, "Provisional": 0, "Total": 0}, "Liberty Dist 1": {"Election Day": 0, "Absentee": 1, "Provisional": 0, "Total": 1}, "Liberty Dist 2": {"Election Day": 0, "Absentee": 1, "Provisional": 0, "Total": 1}, "Lincoln": {"Election Day": 0, "Absentee": 0, "Provisional": 0, "Total": 0}, "Port Vue Dist 1": {"Election Day": 0, "Absentee": 4, "Provisional": 0, "Total": 4}, "Port Vue Dist 2": {"Election Day": 0, "Absentee": 0, "Provisional": 0, "Total": 0}, "Port Vue Dist 3": {"Election Day": 0, "Absentee": 1, "Provisional": 0, "Total": 1}, "Port Vue Dist 4": {"Election Day": 0, "Absentee": 0, "Provisional": 0, "Total": 0}}