{"Marshall Dist 1": {"Election Day": 0, "Absentee": 87, "Provisional": 0, "Total": 87}, "Marshall Dist 2": {"Election Day": 0, "Absentee": 83, "Provisional": 0, "Total": 83}, "Marshall Dist 3": {"Election Day": 0, "Absentee": 84, "Provisional": 0, "Total": 84}, "Marshall Dist 4": {"Election Day": 0, "Absentee": 141, "Provisional": 0, "Total": 141}, "Marshall Dist 5": {"Election Day": 0, "Absentee": 79, "Provisional": 0, "Total": 79}, "Marshall Dist 6": {"Election Day": 0, "Absentee": 98, "Provisional": 0, "Total": 98}, "Marshall Dist 7": {"Election Day": 0, "Absentee": 108, "Provisional": 0, "Total": 108}}