{"ASPINWALL DIST 1": {"Election Day": 12, "Absentee": 0, "Provisional": 0, "Total": 12}, "ASPINWALL DIST 2": {"Election Day": 14, "Absentee": 2, "Provisional": 0, "Total": 16}, "ASPINWALL DIST 3": {"Election Day": 9, "Absentee": 2, "Provisional": 0, "Total": 11}, "BLAWNOX": {"Election Day": 6, "Absentee": 1, "Provisional": 0, "Total": 7}, "FOX CHAPEL DIST 1": {"Election Day": 16, "Absentee": 6, "Provisional": 0, "Total": 22}, "FOX CHAPEL DIST 2": {"Election Day": 12, "Absentee": 4, "Provisional": 0, "Total": 16}, "FOX CHAPEL DIST 3": {"Election Day": 13, "Absentee": 4, "Provisional": 1, "Total": 18}, "FOX CHAPEL DIST 4": {"Election Day": 22, "Absentee": 11, "Provisional": 0, "Total": 33}, "FOX CHAPEL DIST 5": {"Election Day": 13, "Absentee": 4, "Provisional": 0, "Total": 17}, "INDIANA DIST 1": {"Election Day": 11, "Absentee": 2, "Provisional": 0, "Total": 13}, "INDIANA DIST 2": {"Election Day": 13, "Absentee": 7, "Provisional": 0, "Total": 20}, "INDIANA DIST 3": {"Election Day": 13, "Absentee": 5, "Provisional": 0, "Total": 18}, "INDIANA DIST 4": {"Election Day": 17, "Absentee": 6, "Provisional": 0, "Total": 23}, "INDIANA DIST 5": {"Election Day": 9, "Absentee": 5, "Provisional": 0, "Total": 14}, "OHARA WARD 1 DIST 1": {"Election Day": 6, "Absentee": 8, "Provisional": 0, "Total": 14}, "OHARA WARD 1 DIST 2": {"Election Day": 3, "Absentee": 0, "Provisional": 0, "Total": 3}, "OHARA WARD 2 DIST 1": {"Election Day": 8, "Absentee": 1, "Provisional": 0, "Total": 9}, "OHARA WARD 2 DIST 2": {"Election Day": 8, "Absentee": 5, "Provisional": 0, "Total": 13}, "OHARA WARD 3 DIST 1": {"Election Day": 7, "Absentee": 4, "Provisional": 0, "Total": 11}, "OHARA WARD 3 DIST 2": {"Election Day": 14, "Absentee": 1, "Provisional": 1, "Total": 16}, "OHARA WARD 4 DIST 1": {"Election Day": 4, "Absentee": 4, "Provisional": 1, "Total": 9}, "OHARA WARD 4 DIST 2": {"Election Day": 3, "Absentee": 4, "Provisional": 0, "Total": 7}, "OHARA WARD 5 DIST 1": {"Election Day": 8, "Absentee": 1, "Provisional": 0, "Total": 9}, "OHARA WARD 5 DIST 2": {"Election Day": 14, "Absentee": 3, "Provisional": 0, "Total": 17}, "SHARPSBURG DIST 1": {"Election Day": 7, "Absentee": 2, "Provisional": 0, "Total": 9}, "SHARPSBURG DIST 2": {"Election Day": 13, "Absentee": 0, "Provisional": 0, "Total": 13}, "SHARPSBURG DIST 3": {"Election Day": 21, "Absentee": 1, "Provisional": 0, "Total": 22}}