{"Pleasant Hl Dist 1": {"Election Day": 0, "Absentee": 42, "Provisional": 0, "Total": 42}, "Pleasant Hl Dist 2": {"Election Day": 0, "Absentee": 38, "Provisional": 0, "Total": 38}, "Pleasant Hl Dist 3": {"Election Day": 0, "Absentee": 52, "Provisional": 0, "Total": 52}, "Pleasant Hl Dist 4": {"Election Day": 41, "Absentee": 33, "Provisional": 0, "Total": 74}, "Pleasant Hl Dist 5": {"Election Day": 0, "Absentee": 70, "Provisional": 0, "Total": 70}, "Pleasant Hl Dist 6": {"Election Day": 0, "Absentee": 48, "Provisional": 0, "Total": 48}, "Pleasant Hl Dist 7": {"Election Day": 0, "Absentee": 31, "Provisional": 0, "Total": 31}, "Pleasant Hl Dist 8": {"Election Day": 0, "Absentee": 30, "Provisional": 0, "Total": 30}, "Pleasant Hl Dist 9": {"Election Day": 0, "Absentee": 55, "Provisional": 0, "Total": 55}, "Pleasant Hl Dist 10": {"Election Day": 0, "Absentee": 32, "Provisional": 0, "Total": 32}}